{
  "filename": "anomaly_minimal.md",
  "source_name": "Koji adversarial corpus (accuracy-9)",
  "source_url": null,
  "license": "CC0 — synthetic test fixture",
  "license_url": "https://creativecommons.org/publicdomain/zero/1.0/",
  "attribution": "Koji accuracy lane",
  "original_format": "Markdown (synthetic)",
  "r2_url": null,
  "pages": 1,
  "added_date": "2026-05-27",
  "added_by": "accuracy-9",
  "schema": "sec_filings/schemas/filing_metadata.yaml",
  "anomaly": true,
  "notes": "A document containing a single line of text: 'See attached.' This is the minimal non-empty input — one sentence, no structure, no metadata. Complements anomaly_blank (0 bytes) by testing the boundary between empty and nearly-empty. Tests that a trivially short document produces all-null extraction without crashing. All fields expected null."
}
