{
  "filename": "edgar_10k_036.md",
  "source_name": "SEC EDGAR",
  "source_url": "https://www.sec.gov/Archives/edgar/data/1516513/000151651326000025/docs-20260331.htm",
  "license": "Public Domain (US Government Work)",
  "license_url": "https://www.sec.gov/privacy",
  "attribution": "US Securities and Exchange Commission",
  "original_format": "HTML",
  "r2_url": null,
  "pages": 312,
  "added_date": "2026-04-12",
  "added_by": "corpus-bootstrap",
  "schema": "sec_filings/schemas/filing_metadata.yaml",
  "accession_number": "0001516513-26-000025",
  "cik": "0001516513",
  "notes": "10-K filing for Doximity, Inc. (accession 0001516513-26-000025). Document text produced by piping the EDGAR primary HTML through koji parse (docling); expected JSON is sourced from the EDGAR submission index (authoritative for filer, form type, dates)."
}
